.travis.yml
CHANGES.rst
CONTRIBUTORS.rst
MANIFEST.in
README.rst
base.cfg
bootstrap.py
buildout.cfg
checkouts.cfg
jenkins-base.cfg
jenkins.cfg
setup.py
sources.cfg
travis.cfg
versions.cfg
docs/LICENSE.GPL
docs/LICENSE.rst
src/collective/__init__.py
src/collective.z3cform.rolefield.egg-info/PKG-INFO
src/collective.z3cform.rolefield.egg-info/SOURCES.txt
src/collective.z3cform.rolefield.egg-info/dependency_links.txt
src/collective.z3cform.rolefield.egg-info/entry_points.txt
src/collective.z3cform.rolefield.egg-info/namespace_packages.txt
src/collective.z3cform.rolefield.egg-info/not-zip-safe
src/collective.z3cform.rolefield.egg-info/requires.txt
src/collective.z3cform.rolefield.egg-info/top_level.txt
src/collective/z3cform/__init__.py
src/collective/z3cform/rolefield/__init__.py
src/collective/z3cform/rolefield/configure.zcml
src/collective/z3cform/rolefield/field.py
src/collective/z3cform/rolefield/interfaces.py
src/collective/z3cform/rolefield/localrolefield.py
src/collective/z3cform/rolefield/statefulllocalrolesfield.py
src/collective/z3cform/rolefield/statemapping.py
src/collective/z3cform/rolefield/testing.py
src/collective/z3cform/rolefield/testing.zcml
src/collective/z3cform/rolefield/utils.py
src/collective/z3cform/rolefield/profiles/testing/metadata.xml
src/collective/z3cform/rolefield/profiles/testing/types.xml
src/collective/z3cform/rolefield/profiles/testing/workflows.xml
src/collective/z3cform/rolefield/profiles/testing/types/testingtype.xml
src/collective/z3cform/rolefield/tests/__init__.py
src/collective/z3cform/rolefield/tests/container.py
src/collective/z3cform/rolefield/tests/test_localrolefield.py
src/collective/z3cform/rolefield/tests/test_statefulllocalrolesfield.py
src/collective/z3cform/rolefield/tests/test_utils.py