Metadata-Version: 1.1
Name: collective.z3cform.rolefield
Version: 0.2
Summary: A field for managing local roles
Home-page: http://pypi.python.org/pypi/collective.z3cform.rolefield
Author: Ecreall, Entrouvert, IMIO
Author-email: g.bastien@imio.be
License: GPL
Platform: UNKNOWN
Classifier: Environment :: Web Environment
Classifier: Framework :: Plone
Classifier: Framework :: Plone :: 4.2
Classifier: Framework :: Plone :: 4.3
Classifier: Programming Language :: Python
Classifier: Programming Language :: Python :: 2.7
